src/hmta.py
hmta-1.0.0.dist-info/METADATA
hmta-1.0.0.dist-info/WHEEL
hmta-1.0.0.dist-info/entry_points.txt
hmta-1.0.0.dist-info/licenses/LICENSE
hmta-1.0.0.dist-info/RECORD
