Metadata-Version: 2.1
Name: hmta
Version: 1.0.0
Summary: Do you wanna know how much time would take you to watch an anime? Well, this is your tool.
Project-URL: homepage, https://github.com/rooyca/hmta
Project-URL: issues, https://github.com/rooyca/hmta/issues
Author-email: rooyca <rooyca@gmail.com>
License: MIT
License-File: LICENSE
Classifier: License :: OSI Approved :: MIT License
Classifier: Operating System :: OS Independent
Classifier: Programming Language :: Python :: 3
Requires-Python: >=3.7
